{"user_id": 1926676774, "username": "AlinaVazhenina", "vacancy": "Стажёр-инженер по эксплуатации линейно-кабельных сооружений", "message": "Иван Иванов, +7-999-123-45-67, студент 3 курса, знаю Python", "date": "2026-04-03 11:52:15"}
{"user_id": 1926676774, "username": "AlinaVazhenina", "vacancy": "Стажер направление продаж и развития", "message": "Иван Иванов, +7-999-123-45-67", "date": "2026-04-03 13:53:55"}
{"user_id": 1926676774, "username": "AlinaVazhenina", "vacancy": "Аналитик по внедрению AI", "message": "лялял", "date": "2026-04-03 17:04:41"}
{"user_id": 1243766033, "username": "Unknown", "vacancy": "Юрист", "message": "18", "date": "2026-04-04 14:12:42"}
